docling_onnx_models/__init__.py
docling_onnx_models/_version.py
docling_onnx_models/py.typed
docling_onnx_models/code_formula_model/__init__.py
docling_onnx_models/common/__init__.py
docling_onnx_models/common/base_predictor.py
docling_onnx_models/common/model_utils.py
docling_onnx_models/common/utils.py
docling_onnx_models/document_figure_classifier_model/__init__.py
docling_onnx_models/document_figure_classifier_model/document_figure_classifier_predictor.py
docling_onnx_models/layoutmodel/__init__.py
docling_onnx_models/layoutmodel/labels.py
docling_onnx_models/layoutmodel/layout_predictor.py
docling_onnx_models/tableformer/__init__.py
docling_onnx_models/tableformer/data_management/__init__.py
docling_onnx_models/tableformer/data_management/tf_predictor.py
docling_onnx_models/tableformer/utils/__init__.py
docling_onnx_models-0.1.3.dist-info/licenses/LICENSE
docling_onnx_models-0.1.3.dist-info/METADATA
docling_onnx_models-0.1.3.dist-info/WHEEL
docling_onnx_models-0.1.3.dist-info/top_level.txt
docling_onnx_models-0.1.3.dist-info/RECORD
