Metadata-Version: 2.4
Name: docling-onnx-models
Version: 0.1.3
Summary: ONNX Runtime implementations for Docling AI models
Author-email: IBM Research <docling@zurich.ibm.com>
Maintainer-email: IBM Research <docling@zurich.ibm.com>
License: MIT
Project-URL: Homepage, https://github.com/asmud/docling-onnx-models
Project-URL: Repository, https://github.com/asmud/docling-onnx-models.git
Project-URL: Documentation, https://asmud.github.io/docling-onnx-models/
Project-URL: Changelog, https://github.com/asmud/docling-onnx-models/blob/main/CHANGELOG.md
Project-URL: Bug Reports, https://github.com/asmud/docling-onnx-models/issues
Project-URL: Source Code, https://github.com/asmud/docling-onnx-models
Project-URL: PyPI, https://pypi.org/project/docling-onnx-models/
Keywords: docling,onnx,document,ai,layout,table,classification,ocr,document-processing
Classifier: Development Status :: 4 - Beta
Classifier: Intended Audience :: Developers
Classifier: Intended Audience :: Science/Research
Classifier: License :: OSI Approved :: MIT License
Classifier: Operating System :: MacOS :: MacOS X
Classifier: Operating System :: Microsoft :: Windows
Classifier: Operating System :: POSIX :: Linux
Classifier: Programming Language :: Python :: 3
Classifier: Programming Language :: Python :: 3.10
Classifier: Programming Language :: Python :: 3.11
Classifier: Programming Language :: Python :: 3.12
Classifier: Programming Language :: Python :: 3.13
Classifier: Topic :: Scientific/Engineering :: Artificial Intelligence
Classifier: Topic :: Text Processing
Classifier: Topic :: Software Development :: Libraries :: Python Modules
Requires-Python: >=3.10
License-File: LICENSE
Requires-Dist: onnxruntime>=1.15.0
Requires-Dist: numpy>=1.21.0
Requires-Dist: pillow>=8.3.0
Requires-Dist: opencv-python>=4.5.0
Requires-Dist: pydantic>=2.0.0
Provides-Extra: gpu
Requires-Dist: onnxruntime-gpu>=1.15.0; extra == "gpu"
Provides-Extra: coreml
Requires-Dist: coremltools>=7.0.0; sys_platform == "darwin" and extra == "coreml"
Provides-Extra: dev
Requires-Dist: pytest>=7.0.0; extra == "dev"
Requires-Dist: pytest-cov>=4.0.0; extra == "dev"
Requires-Dist: pytest-xdist>=3.0.0; extra == "dev"
Requires-Dist: black>=23.0.0; extra == "dev"
Requires-Dist: isort>=5.12.0; extra == "dev"
Requires-Dist: flake8>=6.0.0; extra == "dev"
Requires-Dist: mypy>=1.0.0; extra == "dev"
Requires-Dist: pre-commit>=3.0.0; extra == "dev"
Provides-Extra: test
Requires-Dist: pytest>=7.0.0; extra == "test"
Requires-Dist: pytest-cov>=4.0.0; extra == "test"
Requires-Dist: pytest-xdist>=3.0.0; extra == "test"
Requires-Dist: pytest-mock>=3.10.0; extra == "test"
Provides-Extra: docs
Requires-Dist: sphinx>=6.0.0; extra == "docs"
Requires-Dist: sphinx-rtd-theme>=1.2.0; extra == "docs"
Requires-Dist: myst-parser>=2.0.0; extra == "docs"
Requires-Dist: sphinx-autodoc-typehints>=1.23.0; extra == "docs"
Provides-Extra: all
Requires-Dist: docling-onnx-models[coreml,dev,docs,gpu,test]; extra == "all"
Dynamic: license-file
